{
  "description": "项目配置文件。",
  "setting": {
    "urlCheck": true,
    "es6": true,
    "postcss": true,
    "minified": true,
    "newFeature": true,
    "babelSetting": {
      "ignore": [],
      "disablePlugins": [],
      "outputPath": ""
    }
  },
  "compileType": "miniprogram",
  "libVersion": "2.28.0",
  "appid": "wx5d479b4ff17b9bb8",
  "projectname": "chrisHat_Lite",
  "condition": {},
  "packOptions": {
    "ignore": [],
    "include": []
  },
  "editorSetting": {
    "tabIndent": "insertSpaces",
    "tabSize": 2
  }
}